pdmemedit/LICENSE
pdmemedit/README.MD
pdmemedit/__init__.py
pdmemedit/requirements.txt
pdmemedit/thirdparty.json
pdmemedit-0.10.dist-info/LICENSE.rst
pdmemedit-0.10.dist-info/METADATA
pdmemedit-0.10.dist-info/WHEEL
pdmemedit-0.10.dist-info/top_level.txt
pdmemedit-0.10.dist-info/RECORD
