Metadata-Version: 2.1
Name: pdmemedit
Version: 0.10
Summary: Edit/read/observe memory with pymem and pandas
Home-page: https://github.com/hansalemaos/pdmemedit
Author: Johannes Fischer
Author-email: <aulasparticularesdealemaosp@gmail.com>
License: MIT
Keywords: pymem,pandas,assembly,hacking,low-level,cheat engine
Classifier: Development Status :: 4 - Beta
Classifier: Programming Language :: Python :: 3 :: Only
Classifier: Programming Language :: Python :: 3.10
Classifier: Topic :: Scientific/Engineering :: Visualization
Classifier: Topic :: Software Development :: Libraries :: Python Modules
Classifier: Topic :: Utilities
License-File: LICENSE.rst
Requires-Dist: a-pandas-ex-apply-ignore-exceptions
Requires-Dist: a-pandas-ex-dillpickle
Requires-Dist: a-pandas-ex-fastloc
Requires-Dist: a-pandas-ex-numexpr
Requires-Dist: get-consecutive-filename
Requires-Dist: numexpr
Requires-Dist: numpy
Requires-Dist: pandas
Requires-Dist: PrettyColorPrinter
Requires-Dist: psutil
Requires-Dist: Pymem
Requires-Dist: regex
Requires-Dist: tolerant-isinstance
Requires-Dist: useful-functions-easier-life
